PyEFVLib/Boundary.py
PyEFVLib/BoundaryConditions.py
PyEFVLib/CsvSaver.py
PyEFVLib/Element.py
PyEFVLib/Facet.py
PyEFVLib/Grid.py
PyEFVLib/GridData.py
PyEFVLib/InnerFace.py
PyEFVLib/LinearSystem.py
PyEFVLib/MSHReader.py
PyEFVLib/MeshioSaver.py
PyEFVLib/OuterFace.py
PyEFVLib/Point.py
PyEFVLib/ProblemData.py
PyEFVLib/Region.py
PyEFVLib/Saver.py
PyEFVLib/Shape.py
PyEFVLib/Solver.py
PyEFVLib/Vertex.py
PyEFVLib/VtmSaver.py
PyEFVLib/VtuSaver.py
PyEFVLib/XDMFReader.py
PyEFVLib/__init__.py
PyEFVLib-1.0.7.dist-info/LICENSE
PyEFVLib-1.0.7.dist-info/METADATA
PyEFVLib-1.0.7.dist-info/WHEEL
PyEFVLib-1.0.7.dist-info/top_level.txt
PyEFVLib-1.0.7.dist-info/RECORD
