Metadata-Version: 2.1
Name: PyEFVLib
Version: 1.0.7
Summary: A library that facilitates the implementation of the Element-based Finite Volumes Method (EbFVM) to solve partial differential equations (PDEs)
Home-page: https://github.com/GustavoExel/PyEFVLib
Author: Gustavo Exel
Author-email: gustavoexelgpe@gmail.com
License: UNKNOWN
Platform: UNKNOWN
Classifier: Programming Language :: Python :: 3
Classifier: Programming Language :: Python :: 3.6
Classifier: Programming Language :: Python :: 3.7
Classifier: Programming Language :: Python :: 3.8
Classifier: License :: OSI Approved :: MIT License
Classifier: Operating System :: OS Independent
Requires-Dist: numpy (~=1.19.2)
Requires-Dist: pandas (~=1.1.2)
Requires-Dist: scipy (~=1.5.2)
Requires-Dist: meshio (~=4.3.4)
Requires-Dist: h5py (~=3.2.1)
Requires-Dist: xmltodict (~=0.12.0)
